odoo/addons/partner_permanent_certificate/README.rst
odoo/addons/partner_permanent_certificate/__init__.py
odoo/addons/partner_permanent_certificate/__manifest__.py
odoo/addons/partner_permanent_certificate/data/res_partner_id_category_data.xml
odoo/addons/partner_permanent_certificate/i18n/partner_permanent_certificate.pot
odoo/addons/partner_permanent_certificate/i18n/pt.po
odoo/addons/partner_permanent_certificate/migrations/14.0.1.1.0/pre-migration.py
odoo/addons/partner_permanent_certificate/models/__init__.py
odoo/addons/partner_permanent_certificate/models/res_partner.py
odoo/addons/partner_permanent_certificate/readme/CONTRIBUTORS.rst
odoo/addons/partner_permanent_certificate/readme/DESCRIPTION.rst
odoo/addons/partner_permanent_certificate/readme/USAGE.rst
odoo/addons/partner_permanent_certificate/static/description/icon.png
odoo/addons/partner_permanent_certificate/static/description/index.html
odoo/addons/partner_permanent_certificate/tests/__init__.py
odoo/addons/partner_permanent_certificate/tests/test_partner_perm_certificate.py
odoo/addons/partner_permanent_certificate/views/res_partner_view.xml
odoo14_addon_partner_permanent_certificate-14.0.1.1.1.dev3.dist-info/METADATA
odoo14_addon_partner_permanent_certificate-14.0.1.1.1.dev3.dist-info/WHEEL
odoo14_addon_partner_permanent_certificate-14.0.1.1.1.dev3.dist-info/top_level.txt
odoo14_addon_partner_permanent_certificate-14.0.1.1.1.dev3.dist-info/RECORD
