Metadata-Version: 2.1
Name: odoo14-addon-partner-permanent-certificate
Version: 14.0.1.1.1.dev3
Summary: Adds field 'Permanent Certificate'
Home-page: https://github.com/OCA/l10n-portugal
Author: Exo Software,Odoo Community Association (OCA)
Author-email: support@odoo-community.org
License: AGPL-3
Platform: UNKNOWN
Classifier: Programming Language :: Python
Classifier: Framework :: Odoo
Classifier: Framework :: Odoo :: 14.0
Classifier: License :: OSI Approved :: GNU Affero General Public License v3
Classifier: Development Status :: 4 - Beta
Requires-Python: >=3.6
Requires-Dist: odoo14-addon-partner-identification
Requires-Dist: odoo <14.1dev,>=14.0a
